corndogs/v1alpha1/corndogs_grpc.py
corndogs/v1alpha1/corndogs_pb2.py
pycorndogs-1.0.0.dist-info/METADATA
pycorndogs-1.0.0.dist-info/WHEEL
pycorndogs-1.0.0.dist-info/RECORD
