Metadata-Version: 2.4
Name: pycorndogs
Version: 1.0.0
Summary: Corndogs python gRPC client
Project-URL: Homepage, https://github.com/catalystcommunity/corndogs
Project-URL: Issues, https://github.com/catalystcommunity/corndogs/issues
Requires-Python: >=3.8
